shadowbar/ProgressBar.py
shadowbar/__init__.py
shadowbar-0.1.3.dist-info/LICENSE
shadowbar-0.1.3.dist-info/METADATA
shadowbar-0.1.3.dist-info/WHEEL
shadowbar-0.1.3.dist-info/top_level.txt
shadowbar-0.1.3.dist-info/RECORD
