Metadata-Version: 2.1
Name: shadowbar
Version: 0.1.3
Summary: A simple to use process based progress bar
Author-email: ShadowCrafter <lkoe@bluewin.ch>
Project-URL: Source Code, https://github.com/shadowcrafter011/shadowbar
Project-URL: Bug Tracker, https://github.com/shadowcrafter011/shadowbar/issues
Classifier: Programming Language :: Python :: 3
Classifier: License :: OSI Approved :: MIT License
Classifier: Operating System :: OS Independent
Requires-Python: >=3.7
License-File: LICENSE
